{
    "A": {
        "brisbane": {
            "0": {
                "0": 9.315381943895481,
                "1": 9.344674692850251,
                "2": 9.522195391816622
            },
            "1": {
                "0": 16.951653326139695,
                "1": 16.716579425770618,
                "2": 16.733957431571955
            },
            "2": {
                "0": 0.971031428633863,
                "1": 0.9160956262833906,
                "2": 0.948111722084428
            },
            "3": {
                "0": 19.21296752513438,
                "1": 18.87313838980508,
                "2": 18.83177279907067
            },
            "4": {
                "0": 0.782205538433909,
                "1": 0.7691357487603954,
                "2": 0.7651520512966227
            },
            "5": {
                "0": 10.146091586437414,
                "1": 9.846425556825494,
                "2": 10.111800004673176
            },
            "6": {
                "0": 0.00015844663204473731,
                "1": 5.781687754747092e-06,
                "2": 0.0007297009698071892
            },
            "7": {
                "0": 19.738423083872213,
                "1": 18.530658634076623,
                "2": 18.836942928219603
            },
            "8": {
                "0": 0.1129387904070483,
                "1": 0.18972663208040802,
                "2": 0.11774936328998618
            },
            "9": {
                "0": 12.853671556469722,
                "1": 13.257069507159152,
                "2": 13.116224212851767
            },
            "10": {
                "0": 17.39822528423639,
                "1": 17.41093908325382,
                "2": 17.48476867218079
            },
            "11": {
                "0": 16.86823418617659,
                "1": 16.795817193584906,
                "2": 16.79207327943787
            },
            "12": {
                "0": 14.522699375542125,
                "1": 14.479716228901747,
                "2": 14.734377986001451
            },
            "13": {
                "0": 18.518420577689888,
                "1": 18.808444031663303,
                "2": 18.709310377547855
            },
            "14": {
                "0": 0.21696126958840942,
                "1": 0.22187590054903678,
                "2": 0.2207792759408769
            },
            "15": {
                "0": 4.608070780567734e-05,
                "1": 3.200000339582932e-07,
                "2": 2.8800027641747664e-06
            },
            "16": {
                "0": 0.002273102854453528,
                "1": 0.01564019015205026,
                "2": 2.0480139808272402e-05
            },
            "17": {
                "0": 0.2265904368700344,
                "1": 0.2363506056952982,
                "2": 0.24426685575570928
            },
            "18": {
                "0": 0.0007070466538983342,
                "1": 0.001659798513465649,
                "2": 3.0420308460168185e-05
            },
            "19": {
                "0": 0.0001881918056439117,
                "1": 0.0013422206260244145,
                "2": 0.0008082377727478586
            }
        },
        "kyiv": {
            "0": {
                "0": 9.292422395537606,
                "1": 9.243235525026579,
                "2": 9.379068859046008
            },
            "1": {
                "0": 16.736512150150226,
                "1": 16.683489253908455,
                "2": 16.732024058440146
            },
            "2": {
                "0": 0.9649702819393705,
                "1": 0.9456166571319389,
                "2": 0.958274157693404
            },
            "3": {
                "0": 18.84506393075133,
                "1": 18.822287794988426,
                "2": 18.90455673400654
            },
            "4": {
                "0": 0.7749797114320323,
                "1": 0.8013576460027971,
                "2": 0.7917501266853925
            },
            "5": {
                "0": 10.057968179403366,
                "1": 10.476587022345152,
                "2": 10.220463262736608
            },
            "6": {
                "0": 0.00014794542617467717,
                "1": 0.00035382473422291075,
                "2": 0.00022475347251458937
            },
            "7": {
                "0": 19.440662375975535,
                "1": 19.806593027192317,
                "2": 19.134136704249393
            },
            "8": {
                "0": 0.20458915977662925,
                "1": 0.2762334376072819,
                "2": 0.14465177231055332
            },
            "9": {
                "0": 13.072189049861155,
                "1": 13.121037918858026,
                "2": 13.069500566521375
            },
            "10": {
                "0": 17.404852271499188,
                "1": 17.40697057002647,
                "2": 17.42578644744749
            },
            "11": {
                "0": 16.898517269232542,
                "1": 16.8714785354523,
                "2": 17.157274649901243
            },
            "12": {
                "0": 14.618123865534498,
                "1": 14.456346468015917,
                "2": 14.50105315057418
            },
            "13": {
                "0": 18.77985408519194,
                "1": 19.09182616936768,
                "2": 18.780765986092383
            },
            "14": {
                "0": 0.18438816616465248,
                "1": 0.20056094785087003,
                "2": 0.18830827322641205
            },
            "15": {
                "0": 9.800003199930902e-07,
                "1": 8.712253012371947e-05,
                "2": 0.0003591630013416204
            },
            "16": {
                "0": 0.0011911930552347995,
                "1": 0.00034325927737311607,
                "2": 8.000000217283526e-08
            },
            "17": {
                "0": 0.24630122459611362,
                "1": 0.21977495235402075,
                "2": 0.22855536063587206
            },
            "18": {
                "0": 1.152004423490404e-05,
                "1": 2.0480139808272402e-05,
                "2": 0.0007685168927669683
            },
            "19": {
                "0": 0.0002509009844198964,
                "1": 7.938210051231659e-05,
                "2": 0.0002832467438594697
            }
        },
        "nazca": {
            "0": {
                "0": 9.276340237898422,
                "1": 9.363161108435117,
                "2": 9.163516916500178
            },
            "1": {
                "0": 16.742917684746846,
                "1": 16.725817068323618,
                "2": 17.136098589172207
            },
            "2": {
                "0": 0.8994287008102089,
                "1": 0.9407231223333762,
                "2": 0.9998419275110706
            },
            "3": {
                "0": 18.712706924766806,
                "1": 18.898989242780978,
                "2": 19.183305071987878
            },
            "4": {
                "0": 0.7368105107407563,
                "1": 0.7386498290721457,
                "2": 1.3345248836781014
            },
            "5": {
                "0": 9.784185473369755,
                "1": 10.205017604109957,
                "2": 9.632112081201248
            },
            "6": {
                "0": 0.00019211025021592665,
                "1": 5.203169799764332e-05,
                "2": 1.6824483304546476e-05
            },
            "7": {
                "0": 18.8436508039856,
                "1": 18.787496106743976,
                "2": 19.607139300605077
            },
            "8": {
                "0": 0.195266255106267,
                "1": 0.11002282699431677,
                "2": 0.23211198040993505
            },
            "9": {
                "0": 13.269645389752505,
                "1": 13.226980661016622,
                "2": 13.245130684726014
            },
            "10": {
                "0": 17.854947264261593,
                "1": 17.88371291548974,
                "2": 17.42613247668248
            },
            "11": {
                "0": 17.090663150580145,
                "1": 17.006937022089367,
                "2": 17.435108353875414
            },
            "12": {
                "0": 14.885229549354637,
                "1": 14.984904403092637,
                "2": 14.537674736434454
            },
            "13": {
                "0": 18.987727828500883,
                "1": 17.879073354249957,
                "2": 19.215225997159397
            },
            "14": {
                "0": 0.3373243806002308,
                "1": 0.19964579872554702,
                "2": 0.2283703405380006
            },
            "15": {
                "0": 0.0005314741614961052,
                "1": 7.938210051231659e-05,
                "2": 0.00022899748043678052
            },
            "16": {
                "0": 0.0045958649836295995,
                "1": 0.0003809283711890942,
                "2": 0.00020001333542717277
            },
            "17": {
                "0": 7.918263269825546e-05,
                "1": 0.24907469816194758,
                "2": 0.24036557500611244
            },
            "18": {
                "0": 0.0007922292310023407,
                "1": 0.0005314741614961052,
                "2": 0.00014792729427587012
            },
            "19": {
                "0": 0.0005249718714825692,
                "1": 3.200034133567231e-05,
                "2": 0.0001280054618669913
            }
        }
    },
    "C": {
        "brisbane": {
            "0": {
                "0": 9.376815212846159,
                "1": 9.217616428903646,
                "2": 9.383716754047827
            },
            "1": {
                "0": 16.853742091706547,
                "1": 16.83690859711676,
                "2": 16.875584211096317
            },
            "2": {
                "0": 0.858431844769258,
                "1": 0.8359518652429841,
                "2": 0.8849029696769009
            },
            "3": {
                "0": 18.695886155056247,
                "1": 18.535391428335952,
                "2": 18.631011237063458
            },
            "4": {
                "0": 0.7295510089756583,
                "1": 0.7402099308762444,
                "2": 0.723662389975989
            },
            "5": {
                "0": 10.26970968028191,
                "1": 10.258914103619203,
                "2": 10.31349315579445
            },
            "6": {
                "0": 0.00013780422068636333,
                "1": 0.00020003105473775235,
                "2": 6.052934989021763e-05
            },
            "7": {
                "0": 18.6108146371109,
                "1": 18.703166527626905,
                "2": 18.575269322566754
            },
            "8": {
                "0": 0.26931420531191824,
                "1": 0.28962480533229373,
                "2": 0.291015609833274
            },
            "9": {
                "0": 13.320056084433839,
                "1": 13.32940869887544,
                "2": 13.376446890122802
            },
            "10": {
                "0": 17.44138591712357,
                "1": 17.385943009615104,
                "2": 17.425296413772493
            },
            "11": {
                "0": 16.859306643372026,
                "1": 16.878841206397276,
                "2": 16.859436800691153
            },
            "12": {
                "0": 14.541615317871907,
                "1": 14.535412848751895,
                "2": 14.539262016018219
            },
            "13": {
                "0": 18.947131089867355,
                "1": 19.084040868054494,
                "2": 19.06351377955461
            },
            "14": {
                "0": 0.20569551671916458,
                "1": 0.21062302060511587,
                "2": 0.20609300371773906
            },
            "15": {
                "0": 0.0014371686162985599,
                "1": 0.0018131160614486795,
                "2": 0.001405158279727748
            },
            "16": {
                "0": 0.0003075515305462368,
                "1": 0.001513263475966354,
                "2": 0.0005249718714825692
            },
            "17": {
                "0": 0.22407562736621825,
                "1": 0.2221286258418877,
                "2": 0.2097994714470151
            },
            "18": {
                "0": 9.522302249400337e-05,
                "1": 9.680031232438702e-06,
                "2": 2.0480139808272402e-05
            },
            "19": {
                "0": 1.6820094302038256e-05,
                "1": 3.920005121309982e-06,
                "2": 1.4580070856765482e-05
            }
        },
        "kyiv": {
            "0": {
                "0": 9.274360745429423,
                "1": 9.221061922389692,
                "2": 9.404691336735205
            },
            "1": {
                "0": 16.667414231108033,
                "1": 16.756863949054097,
                "2": 16.664795038495427
            },
            "2": {
                "0": 0.992843657908694,
                "1": 1.0176886078876972,
                "2": 1.020966097604725
            },
            "3": {
                "0": 18.695418391014,
                "1": 18.73989306818531,
                "2": 18.732646781940048
            },
            "4": {
                "0": 0.7917334865759894,
                "1": 0.7889794451699623,
                "2": 0.773896830324402
            },
            "5": {
                "0": 10.403492414850668,
                "1": 10.255879823334412,
                "2": 10.282587545818215
            },
            "6": {
                "0": 0.00035382473422291075,
                "1": 0.0004500527687725589,
                "2": 0.0006698539716764942
            },
            "7": {
                "0": 19.052426755517967,
                "1": 19.098217345812664,
                "2": 19.18804125200743
            },
            "8": {
                "0": 0.18349542535262264,
                "1": 0.18323179120193367,
                "2": 0.1780887959397159
            },
            "9": {
                "0": 11.525851987702206,
                "1": 11.437618593188532,
                "2": 11.435305742514819
            },
            "10": {
                "0": 17.857471365440418,
                "1": 17.86129293401692,
                "2": 17.892770374857353
            },
            "11": {
                "0": 16.9538917053577,
                "1": 16.940606082894583,
                "2": 16.947548936200885
            },
            "12": {
                "0": 14.488294158886667,
                "1": 14.46814569624875,
                "2": 14.466594881366975
            },
            "13": {
                "0": 18.841006426779245,
                "1": 18.88196636202103,
                "2": 18.83396546183486
            },
            "14": {
                "0": 0.18137965787696864,
                "1": 0.19977641431458548,
                "2": 0.18063113332192574
            },
            "15": {
                "0": 0.0033493610791639483,
                "1": 0.003702571939844461,
                "2": 0.003155500459487842
            },
            "16": {
                "0": 4.418065063834919e-05,
                "1": 0.0005713288137149039,
                "2": 0.0001445069608590841
            },
            "17": {
                "0": 0.18229383019439815,
                "1": 0.17364303269786355,
                "2": 0.17018729618339629
            },
            "18": {
                "0": 0.0002738049905820425,
                "1": 0.0004090357730483496,
                "2": 4.500006749068482e-06
            },
            "19": {
                "0": 0.0001445069608590841,
                "1": 4.232059700588157e-05,
                "2": 7.938210051231659e-05
            }
        },
        "nazca": {
            "0": {
                "0": 9.36457675186972,
                "1": 9.2828097439687,
                "2": 9.342555626037612
            },
            "1": {
                "0": 16.5960817263969,
                "1": 16.63931143421732,
                "2": 16.654597602971048
            },
            "2": {
                "0": 0.9254117538485114,
                "1": 0.9234510587476719,
                "2": 0.9618806603538944
            },
            "3": {
                "0": 18.77575740991474,
                "1": 18.787920398492904,
                "2": 18.78961942312852
            },
            "4": {
                "0": 0.731278221073132,
                "1": 0.7544585046243486,
                "2": 0.7151071261416104
            },
            "5": {
                "0": 10.125032684432291,
                "1": 10.042172681675478,
                "2": 10.010649895186914
            },
            "6": {
                "0": 6.051318854513599e-05,
                "1": 0.0002928596035190346,
                "2": 0.0005848850565731006
            },
            "7": {
                "0": 18.52266968264742,
                "1": 18.31672486879308,
                "2": 18.48198583733842
            },
            "8": {
                "0": 0.1736654550904208,
                "1": 0.1762791120331753,
                "2": 0.1816598186310434
            },
            "9": {
                "0": 12.90962836871864,
                "1": 12.964749229364534,
                "2": 12.893164502003943
            },
            "10": {
                "0": 17.40777918615389,
                "1": 17.433892097317,
                "2": 17.402567399467152
            },
            "11": {
                "0": 16.870008641360744,
                "1": 16.859707223776013,
                "2": 16.844742018330013
            },
            "12": {
                "0": 14.586047275650916,
                "1": 14.578796531912735,
                "2": 14.603474345902272
            },
            "13": {
                "0": 18.84938882891939,
                "1": 18.857370143547975,
                "2": 18.88220577651527
            },
            "14": {
                "0": 0.2068890578457354,
                "1": 0.20056094785087003,
                "2": 0.1973015581281922
            },
            "15": {
                "0": 0.0003920512373246643,
                "1": 0.0005185096235037663,
                "2": 0.0011049069995950934
            },
            "16": {
                "0": 0.0001411266390060669,
                "1": 0.0005380164940653603,
                "2": 2.4500200082299035e-05
            },
            "17": {
                "0": 0.24252935258743438,
                "1": 0.25363085578279077,
                "2": 0.241085834066462
            },
            "18": {
                "0": 0.016728369600066184,
                "1": 0.014383414262974667,
                "2": 0.012984618158102437
            },
            "19": {
                "0": 1.8000107998010495e-05,
                "1": 8.82002592921937e-06,
                "2": 1.5680081952025582e-05
            }
        }
    }
}